jupyterlab_codeium/__init__.py
jupyterlab_codeium/_version.py
jupyterlab_codeium-0.1.1.data/data/share/jupyter/labextensions/jupyterlab-codeium/package.json
jupyterlab_codeium-0.1.1.data/data/share/jupyter/labextensions/jupyterlab-codeium/schemas/jupyterlab-codeium/inline-provider.json
jupyterlab_codeium-0.1.1.data/data/share/jupyter/labextensions/jupyterlab-codeium/schemas/jupyterlab-codeium/package.json.orig
jupyterlab_codeium-0.1.1.data/data/share/jupyter/labextensions/jupyterlab-codeium/static/24.c56cceee6627ed5307ef.js
jupyterlab_codeium-0.1.1.data/data/share/jupyter/labextensions/jupyterlab-codeium/static/344.00cc910cd5f1e7eb05c1.js
jupyterlab_codeium-0.1.1.data/data/share/jupyter/labextensions/jupyterlab-codeium/static/362.4c151fdf52c1dc37b072.js
jupyterlab_codeium-0.1.1.data/data/share/jupyter/labextensions/jupyterlab-codeium/static/728.81e04a89b9ac99ff97ca.js
jupyterlab_codeium-0.1.1.data/data/share/jupyter/labextensions/jupyterlab-codeium/static/960.085bf60b84e6f4342a4d.js
jupyterlab_codeium-0.1.1.data/data/share/jupyter/labextensions/jupyterlab-codeium/static/967.f489a8cb1e8d766f8fc6.js
jupyterlab_codeium-0.1.1.data/data/share/jupyter/labextensions/jupyterlab-codeium/static/remoteEntry.c0bc4a0fb1e039fb7a5c.js
jupyterlab_codeium-0.1.1.data/data/share/jupyter/labextensions/jupyterlab-codeium/static/style.js
jupyterlab_codeium-0.1.1.data/data/share/jupyter/labextensions/jupyterlab-codeium/static/third-party-licenses.json
jupyterlab_codeium-0.1.1.data/data/share/jupyter/labextensions/jupyterlab-codeium/install.json
jupyterlab_codeium-0.1.1.dist-info/METADATA
jupyterlab_codeium-0.1.1.dist-info/WHEEL
jupyterlab_codeium-0.1.1.dist-info/licenses/LICENSE
jupyterlab_codeium-0.1.1.dist-info/RECORD
