Metadata-Version: 2.3
Name: jupyterlab_codeium
Version: 0.1.1
Dynamic: Keywords
Summary: A JupyterLab extension to get AI code completions with Codeium
Project-URL: Homepage, https://github.com/jtpio/jupyterlab-codeium
Project-URL: Bug Tracker, https://github.com/jtpio/jupyterlab-codeium/issues
Project-URL: Repository, https://github.com/jtpio/jupyterlab-codeium.git
Author: Jeremy Tuloup
License: BSD 3-Clause License
License-File: LICENSE
Classifier: Framework :: Jupyter
Classifier: Framework :: Jupyter :: JupyterLab
Classifier: Framework :: Jupyter :: JupyterLab :: 4
Classifier: Framework :: Jupyter :: JupyterLab :: Extensions
Classifier: Framework :: Jupyter :: JupyterLab :: Extensions :: Prebuilt
Classifier: License :: OSI Approved :: BSD License
Classifier: Programming Language :: Python
Classifier: Programming Language :: Python :: 3
Classifier: Programming Language :: Python :: 3.8
Classifier: Programming Language :: Python :: 3.9
Classifier: Programming Language :: Python :: 3.10
Classifier: Programming Language :: Python :: 3.11
Classifier: Programming Language :: Python :: 3.12
Requires-Python: >=3.8
